immucellai2/Deconvolution.py
immucellai2/Drawplot.py
immucellai2/ObtainCategory.py
immucellai2/PrepareData.py
immucellai2/Time.py
immucellai2/__init__.py
immucellai2/myclasses.py
immucellai2/myconfig/Celltype.category
immucellai2/myconfig/MarkerUsedDeconvolution.txt
immucellai2/myconfig/reference_normalCelltypes.txt
immucellai2/myconfig/reference_tumorCelltypes.txt
immucellai2-2.1.24.dist-info/METADATA
immucellai2-2.1.24.dist-info/WHEEL
immucellai2-2.1.24.dist-info/entry_points.txt
immucellai2-2.1.24.dist-info/top_level.txt
immucellai2-2.1.24.dist-info/RECORD
