Metadata-Version: 2.4
Name: immucellai2
Version: 2.1.24
Summary: A tool for immune cell type deconvolution
Home-page: https://github.com/VyvyanYjm/ImmuCellAI2.0
Author: YangJingmin
Author-email: yangjingmin2021@163.com
License: MIT
Classifier: Programming Language :: Python :: 3
Classifier: Operating System :: OS Independent
Requires-Python: >=3.7
Requires-Dist: numpy
Requires-Dist: pandas
Requires-Dist: openpyxl
Requires-Dist: matplotlib
